aws_stuff_doer/__init__.py
aws_stuff_doer/cmd/__init__.py
aws_stuff_doer/cmd/aws_auth.py
aws_stuff_doer/cmd/config.py
aws_stuff_doer/cmd/s3stuff/__init__.py
aws_stuff_doer/cmd/s3stuff/s3app.css
aws_stuff_doer/cmd/s3stuff/s3stuff.py
aws_stuff_doer/main.py
aws_stuff_doer-0.2.3.dist-info/LICENSE
aws_stuff_doer-0.2.3.dist-info/METADATA
aws_stuff_doer-0.2.3.dist-info/WHEEL
aws_stuff_doer-0.2.3.dist-info/entry_points.txt
aws_stuff_doer-0.2.3.dist-info/RECORD
