Metadata-Version: 2.3
Name: aws-stuff-doer
Version: 0.2.3
Summary: ASD is a utility to help manage your AWS projects and sso sessions.
License: MIT
Author: Aaron West
Author-email: aphexlog@gmail.com
Requires-Python: >=3.11,<4.0
Classifier: License :: OSI Approved :: MIT License
Classifier: Programming Language :: Python :: 3
Classifier: Programming Language :: Python :: 3.11
Classifier: Programming Language :: Python :: 3.12
Classifier: Programming Language :: Python :: 3.13
Requires-Dist: aws-cdk-lib (>=2.126.0,<3.0.0)
Requires-Dist: boto3 (>=1.34.36,<2.0.0)
Requires-Dist: boto3-stubs (>=1.34.36,<2.0.0)
Requires-Dist: gitpython (>=3.1.41,<4.0.0)
Requires-Dist: lark (>=1.1.9,<2.0.0)
Requires-Dist: mypy-boto3-s3 (>=1.34.120,<2.0.0)
Requires-Dist: mypy-boto3-sts (>=1.34.0,<2.0.0)
Requires-Dist: setuptools (>=69.0.3,<70.0.0)
Requires-Dist: textual (>=0.71.0,<0.72.0)
Requires-Dist: typer (>=0.15.1,<0.16.0)
Project-URL: Repository, https://github.com/aphexlog/aws-stuff-doer
